cli/VERSION.txt
cli/__init__.py
cli/soos.py
soos_sca-1.7.15.dist-info/LICENSE
soos_sca-1.7.15.dist-info/METADATA
soos_sca-1.7.15.dist-info/WHEEL
soos_sca-1.7.15.dist-info/entry_points.txt
soos_sca-1.7.15.dist-info/top_level.txt
soos_sca-1.7.15.dist-info/RECORD
